unstructured_api_tools/__init__.py
unstructured_api_tools/__version__.py
unstructured_api_tools/cli.py
unstructured_api_tools/pipelines/__init__.py
unstructured_api_tools/pipelines/api_conventions.py
unstructured_api_tools/pipelines/convert.py
unstructured_api_tools/pipelines/lint.py
unstructured_api_tools/pipelines/templates/pipeline_api.txt
unstructured_api_tools/pipelines/templates/pipeline_app.txt
unstructured_api_tools-0.10.11.dist-info/LICENSE.md
unstructured_api_tools-0.10.11.dist-info/METADATA
unstructured_api_tools-0.10.11.dist-info/WHEEL
unstructured_api_tools-0.10.11.dist-info/entry_points.txt
unstructured_api_tools-0.10.11.dist-info/top_level.txt
unstructured_api_tools-0.10.11.dist-info/RECORD
