Metadata-Version: 2.1
Name: unstructured-api-tools
Version: 0.10.11
Summary: A library that prepares raw documents for downstream ML tasks.
Home-page: https://github.com/Unstructured-IO/unstructured-api-tools
Author: Unstructured Technologies
Author-email: mrobinson@unstructuredai.io
License: Apache-2.0
Keywords: NLP PDF HTML CV XML parsing preprocessing
Platform: UNKNOWN
Classifier: Development Status :: 4 - Beta
Classifier: Intended Audience :: Developers
Classifier: Intended Audience :: Education
Classifier: Intended Audience :: Science/Research
Classifier: License :: OSI Approved :: Apache Software License
Classifier: Operating System :: OS Independent
Classifier: Programming Language :: Python :: 3
Classifier: Programming Language :: Python :: 3.8
Classifier: Programming Language :: Python :: 3.9
Classifier: Topic :: Scientific/Engineering :: Artificial Intelligence
Requires-Python: >=3.8.0
Requires-Dist: click (>=8.1)
Requires-Dist: fastapi
Requires-Dist: Jinja2
Requires-Dist: mypy (>=0.99)
Requires-Dist: nbconvert
Requires-Dist: python-multipart
Requires-Dist: pandas
Requires-Dist: types-requests
Requires-Dist: types-ujson
Requires-Dist: uvicorn[standard]
Requires-Dist: autoflake
